auto_lm/__init__.py
auto_lm/analyzer.py
auto_lm/utils.py
auto_lm-0.1.0.dist-info/licenses/LICENSE
auto_lm-0.1.0.dist-info/METADATA
auto_lm-0.1.0.dist-info/WHEEL
auto_lm-0.1.0.dist-info/top_level.txt
auto_lm-0.1.0.dist-info/RECORD
