Metadata-Version: 2.4
Name: auto_lm
Version: 0.1.0
Summary: Advanced Automated EDA Library for comprehensive data analysis
Home-page: https://github.com/yourusername/auto_lm
Author: Louati Mahdi
Author-email: your_email@example.com
Project-URL: Bug Reports, https://github.com/yourusername/auto_lm/issues
Project-URL: Source, https://github.com/yourusername/auto_lm
Keywords: eda exploratory-data-analysis data-science statistics machine-learning
Classifier: Development Status :: 3 - Alpha
Classifier: Intended Audience :: Developers
Classifier: Topic :: Software Development :: Libraries :: Python Modules
Classifier: License :: OSI Approved :: MIT License
Classifier: Programming Language :: Python :: 3
Classifier: Programming Language :: Python :: 3.7
Classifier: Programming Language :: Python :: 3.8
Classifier: Programming Language :: Python :: 3.9
Classifier: Programming Language :: Python :: 3.10
Requires-Python: >=3.7
License-File: LICENSE
Requires-Dist: pandas>=1.3.0
Requires-Dist: numpy>=1.21.0
Requires-Dist: scipy>=1.7.0
Requires-Dist: tabulate>=0.8.9
Requires-Dist: statsmodels>=0.12.0
Requires-Dist: seaborn>=0.11.0
Dynamic: author
Dynamic: author-email
Dynamic: classifier
Dynamic: description
Dynamic: description-content-type
Dynamic: home-page
Dynamic: keywords
Dynamic: license-file
Dynamic: project-url
Dynamic: requires-dist
Dynamic: requires-python
Dynamic: summary
